[
  {
    "comments": false,
    "reminders": false,
    "selections": false,
    "verseEdits": false,
    "contextId": {
      "occurrenceNote": "This speaks of the grave as if it were a person that swallows humans and takes them down to the place of the dead. (See: [[rc://en/ta/man/translate/figs-personification]])",
      "reference": {
        "bookId": "pro",
        "chapter": 1,
        "verse": 12
      },
      "tool": "translationNotes",
      "groupId": "figs-personification",
      "glQuote": "Let us swallow ... like Sheol takes away",
      "occurrence": 0
    }
  },
  {
    "comments": false,
    "reminders": false,
    "selections": false,
    "verseEdits": false,
    "contextId": {
      "occurrenceNote": "In 1:20-1:33 Wisdom is spoken of as if it were a woman speaking to the people. (See: [[rc://en/ta/man/translate/figs-personification]])",
      "reference": {
        "bookId": "pro",
        "chapter": 1,
        "verse": 20
      },
      "tool": "translationNotes",
      "groupId": "figs-personification",
      "glQuote": "General Information:",
      "occurrence": 0
    }
  },
  {
    "comments": false,
    "reminders": false,
    "selections": false,
    "verseEdits": false,
    "contextId": {
      "occurrenceNote": "If your language does not allow you to treat wisdom as a woman shouting to the people in the city, you might try something like \"Grandmother Wisdom cries aloud\" or \"Honored Miss Wisdom cries aloud\" or \"Wisdom is like a woman who cries aloud\" (See: [[rc://en/ta/man/translate/figs-personification]])",
      "reference": {
        "bookId": "pro",
        "chapter": 1,
        "verse": 20
      },
      "tool": "translationNotes",
      "groupId": "figs-personification",
      "glQuote": "Wisdom cries aloud",
      "occurrence": 0
    }
  },
  {
    "comments": false,
    "reminders": false,
    "selections": false,
    "verseEdits": false,
    "contextId": {
      "occurrenceNote": "Wisdom continues to speak. (See: [[rc://en/ta/man/translate/figs-personification]])",
      "reference": {
        "bookId": "pro",
        "chapter": 1,
        "verse": 23
      },
      "tool": "translationNotes",
      "groupId": "figs-personification",
      "glQuote": "General Information:",
      "occurrence": 0
    }
  },
  {
    "comments": false,
    "reminders": false,
    "selections": false,
    "verseEdits": false,
    "contextId": {
      "occurrenceNote": "Wisdom continues speaking. (See: [[rc://en/ta/man/translate/figs-personification]])",
      "reference": {
        "bookId": "pro",
        "chapter": 1,
        "verse": 28
      },
      "tool": "translationNotes",
      "groupId": "figs-personification",
      "occurrence": 0
    }
  },
  {
    "comments": false,
    "reminders": false,
    "selections": false,
    "verseEdits": false,
    "contextId": {
      "occurrenceNote": "This speaks of \"discretion\" and \"understanding\" as if they were persons who could watch over someone else. Both statements mean basically the same thing. Alternate translation: \"Because you think carefully and understand what is right and wrong you will be safe\" (See: [[rc://en/ta/man/translate/figs-personification]] and [[rc://en/ta/man/translate/figs-parallelism]])",
      "reference": {
        "bookId": "pro",
        "chapter": 2,
        "verse": 11
      },
      "tool": "translationNotes",
      "groupId": "figs-personification",
      "glQuote": "Discretion will watch over you, understanding will guard you",
      "occurrence": 0
    }
  },
  {
    "comments": false,
    "reminders": false,
    "selections": false,
    "verseEdits": false,
    "contextId": {
      "occurrenceNote": "\"They\" refers to discretion and understanding, which are spoken of as if they were persons who could rescue someone else. Alternate translation: \"You will know to stay away from what is evil\" (See: [[rc://en/ta/man/translate/figs-personification]])",
      "reference": {
        "bookId": "pro",
        "chapter": 2,
        "verse": 12
      },
      "tool": "translationNotes",
      "groupId": "figs-personification",
      "glQuote": "They will rescue you from the way of evil",
      "occurrence": 0
    }
  },
  {
    "comments": false,
    "reminders": false,
    "selections": false,
    "verseEdits": false,
    "contextId": {
      "occurrenceNote": "The writer speaks of wisdom and discretion as if they were people who save the one who possesses them. Alternate translation: \"If you have wisdom and discretion, you will save yourself\" (See: [[rc://en/ta/man/translate/figs-personification]])",
      "reference": {
        "bookId": "pro",
        "chapter": 2,
        "verse": 16
      },
      "tool": "translationNotes",
      "groupId": "figs-personification",
      "glQuote": "Wisdom and discretion will save you",
      "occurrence": 0
    }
  },
  {
    "comments": false,
    "reminders": false,
    "selections": false,
    "verseEdits": false,
    "contextId": {
      "occurrenceNote": "The writer speaks of \"covenant faithfulness\" and \"trustworthiness\" as if they were people who could leave someone. The abstract nouns \"faithfulness\" and \"trustworthiness\" can be stated as \"faithful\" and \"trustworthy.\" And, the negative command can be stated positively. Alternate translation: \"Always be trustworthy and be faithful to the covenant\" (See: [[rc://en/ta/man/translate/figs-personification]] and [[rc://en/ta/man/translate/figs-abstractnouns]])",
      "reference": {
        "bookId": "pro",
        "chapter": 3,
        "verse": 3
      },
      "tool": "translationNotes",
      "groupId": "figs-personification",
      "glQuote": "Do not let covenant faithfulness and trustworthiness ever leave you",
      "occurrence": 0
    }
  },
  {
    "comments": false,
    "reminders": false,
    "selections": false,
    "verseEdits": false,
    "contextId": {
      "occurrenceNote": "The author speaks of wisdom as if it were a woman. (See: [[rc://en/ta/man/translate/figs-personification]])",
      "reference": {
        "bookId": "pro",
        "chapter": 3,
        "verse": 15
      },
      "tool": "translationNotes",
      "groupId": "figs-personification",
      "glQuote": "General Information:",
      "occurrence": 0
    }
  },
  {
    "comments": false,
    "reminders": false,
    "selections": false,
    "verseEdits": false,
    "contextId": {
      "occurrenceNote": "The writer speak of the benefits that one gains from having wisdom as if wisdom were a woman who held these qualities in her hands and offered them to people. Alternate translation: \"Wisdom gives a person length of days and riches and honor\" (See: [[rc://en/ta/man/translate/figs-personification]] and [[rc://en/ta/man/translate/figs-metaphor]])",
      "reference": {
        "bookId": "pro",
        "chapter": 3,
        "verse": 16
      },
      "tool": "translationNotes",
      "groupId": "figs-personification",
      "glQuote": "She has the length of her days in her right hand; in her left hand are riches and honor",
      "occurrence": 0
    }
  },
  {
    "comments": false,
    "reminders": false,
    "selections": false,
    "verseEdits": false,
    "contextId": {
      "occurrenceNote": "The writer speaks of wisdom as if it were a woman and of the benefits that wisdom gives a person as if wisdom were leading that person along a path. Alternate translation: \"Wisdom will always treat you kindly and give you peace\" (See: [[rc://en/ta/man/translate/figs-personification]] and [[rc://en/ta/man/translate/figs-metaphor]])",
      "reference": {
        "bookId": "pro",
        "chapter": 3,
        "verse": 17
      },
      "tool": "translationNotes",
      "groupId": "figs-personification",
      "glQuote": "Her ways are ways of kindness and all her paths are peace",
      "occurrence": 0
    }
  },
  {
    "comments": false,
    "reminders": false,
    "selections": false,
    "verseEdits": false,
    "contextId": {
      "occurrenceNote": "The writer speaks of wisdom as if it were a woman who protects the person who is faithful to her. (See: [[rc://en/ta/man/translate/figs-personification]] and [[rc://en/ta/man/translate/figs-metaphor]])",
      "reference": {
        "bookId": "pro",
        "chapter": 4,
        "verse": 6
      },
      "tool": "translationNotes",
      "groupId": "figs-personification",
      "glQuote": "do not abandon wisdom and she will watch over you; love her and she will keep you safe",
      "occurrence": 0
    }
  },
  {
    "comments": false,
    "reminders": false,
    "selections": false,
    "verseEdits": false,
    "contextId": {
      "occurrenceNote": "The writer speaks of wisdom as if it were a woman and of wisdom giving great honor to a person as if wisdom lifted that person to a high position. Alternate translation: \"If you cherish wisdom, she will give you great honor\" (See: [[rc://en/ta/man/translate/figs-personification]] and [[rc://en/ta/man/translate/figs-metaphor]])",
      "reference": {
        "bookId": "pro",
        "chapter": 4,
        "verse": 8
      },
      "tool": "translationNotes",
      "groupId": "figs-personification",
      "glQuote": "Cherish wisdom and she will exalt you",
      "occurrence": 0
    }
  },
  {
    "comments": false,
    "reminders": false,
    "selections": false,
    "verseEdits": false,
    "contextId": {
      "occurrenceNote": "The writer speaks of wisdom as if it were a woman and of a person valuing wisdom as if the person placed his arms around her. Alternate translation: \"if you love wisdom greatly, wisdom will cause people to honor you\" (See: [[rc://en/ta/man/translate/figs-personification]] and [[rc://en/ta/man/translate/figs-metaphor]])",
      "reference": {
        "bookId": "pro",
        "chapter": 4,
        "verse": 8
      },
      "tool": "translationNotes",
      "groupId": "figs-personification",
      "glQuote": "she will honor you when you embrace her",
      "occurrence": 0
    }
  },
  {
    "comments": false,
    "reminders": false,
    "selections": false,
    "verseEdits": false,
    "contextId": {
      "occurrenceNote": "The writer speaks of a wicked person being unable to avoid the consequences of his iniquities as if those iniquities were people who capture the wicked person. This can be stated in active form. Alternate translation: \"A wicked person's own iniquities will seize him\" or \"A wicked person will be unable to avoid the consequences of his iniquities\" (See: [[rc://en/ta/man/translate/figs-personification]] and [[rc://en/ta/man/translate/figs-metaphor]] and [[rc://en/ta/man/translate/figs-activepassive]])",
      "reference": {
        "bookId": "pro",
        "chapter": 5,
        "verse": 22
      },
      "tool": "translationNotes",
      "groupId": "figs-personification",
      "glQuote": "A wicked person will be seized by his own iniquities",
      "occurrence": 0
    }
  },
  {
    "comments": false,
    "reminders": false,
    "selections": false,
    "verseEdits": false,
    "contextId": {
      "occurrenceNote": "This implies that the disaster is chasing him like a person or an animal, and that it will catch him soon. Alternate translation: \"his disaster will catch him\" (See: [[rc://en/ta/man/translate/figs-personification]])",
      "reference": {
        "bookId": "pro",
        "chapter": 6,
        "verse": 15
      },
      "tool": "translationNotes",
      "groupId": "figs-personification",
      "glQuote": "his disaster will overtake him",
      "occurrence": 0
    }
  },
  {
    "comments": false,
    "reminders": false,
    "selections": false,
    "verseEdits": false,
    "contextId": {
      "occurrenceNote": "Here wisdom is spoken of as if it were a person. Alternate translation: \"Value wisdom as you would love your sister\" (See: [[rc://en/ta/man/translate/figs-personification]])",
      "reference": {
        "bookId": "pro",
        "chapter": 7,
        "verse": 4
      },
      "tool": "translationNotes",
      "groupId": "figs-personification",
      "glQuote": "Say to wisdom, \"You are my sister",
      "occurrence": 0
    }
  },
  {
    "comments": false,
    "reminders": false,
    "selections": false,
    "verseEdits": false,
    "contextId": {
      "occurrenceNote": "Here the quality of understanding is spoken of as if it were a kinsman or relative. Alternate translation: \"treat understanding as you would treat your kinsman\" (See: [[rc://en/ta/man/translate/figs-personification]])",
      "reference": {
        "bookId": "pro",
        "chapter": 7,
        "verse": 4
      },
      "tool": "translationNotes",
      "groupId": "figs-personification",
      "glQuote": "call understanding your kinsman",
      "occurrence": 0
    }
  },
  {
    "comments": false,
    "reminders": false,
    "selections": false,
    "verseEdits": false,
    "contextId": {
      "occurrenceNote": "In chapter 8 wisdom is spoken of as a woman who teaches people how to be wise. Many verses in chapter 8 have parallelisms. (See: [[rc://en/ta/man/translate/figs-personification]] and [[rc://en/ta/man/translate/figs-parallelism]])",
      "reference": {
        "bookId": "pro",
        "chapter": 8,
        "verse": 1
      },
      "tool": "translationNotes",
      "groupId": "figs-personification",
      "glQuote": "General Information:",
      "occurrence": 0
    }
  },
  {
    "comments": false,
    "reminders": false,
    "selections": false,
    "verseEdits": false,
    "contextId": {
      "occurrenceNote": "Here wisdom is imagined as a woman. If a language does not allow this kind of metaphor, other possible translations are: 1) \"Is not wisdom like a woman who calls out?\" 2) \"Does not a woman named Wisdom call out?\" (See: [[rc://en/ta/man/translate/figs-personification]])",
      "reference": {
        "bookId": "pro",
        "chapter": 8,
        "verse": 1
      },
      "tool": "translationNotes",
      "groupId": "figs-personification",
      "glQuote": "Does not Wisdom call out?",
      "occurrence": 0
    }
  },
  {
    "comments": false,
    "reminders": false,
    "selections": false,
    "verseEdits": false,
    "contextId": {
      "occurrenceNote": "This continues to refer to Wisdom, personified as a woman. (See: [[rc://en/ta/man/translate/figs-personification]])",
      "reference": {
        "bookId": "pro",
        "chapter": 8,
        "verse": 3
      },
      "tool": "translationNotes",
      "groupId": "figs-personification",
      "glQuote": "she calls out",
      "occurrence": 0
    }
  },
  {
    "comments": false,
    "reminders": false,
    "selections": false,
    "verseEdits": false,
    "contextId": {
      "occurrenceNote": "Prudence is also represented here as a person. (See: [[rc://en/ta/man/translate/figs-personification]])",
      "reference": {
        "bookId": "pro",
        "chapter": 8,
        "verse": 12
      },
      "tool": "translationNotes",
      "groupId": "figs-personification",
      "glQuote": "I, Wisdom, live with Prudence",
      "occurrence": 0
    }
  },
  {
    "comments": false,
    "reminders": false,
    "selections": false,
    "verseEdits": false,
    "contextId": {
      "occurrenceNote": "Here Wisdom is spoken of as if she were insight. Alternate translation: \"I have insight\" (See: [[rc://en/ta/man/translate/figs-personification]])",
      "reference": {
        "bookId": "pro",
        "chapter": 8,
        "verse": 14
      },
      "tool": "translationNotes",
      "groupId": "figs-personification",
      "glQuote": "I am insight",
      "occurrence": 0
    }
  },
  {
    "comments": false,
    "reminders": false,
    "selections": false,
    "verseEdits": false,
    "contextId": {
      "occurrenceNote": "Wisdom continues to speak. (See: [[rc://en/ta/man/translate/figs-personification]])",
      "reference": {
        "bookId": "pro",
        "chapter": 8,
        "verse": 24
      },
      "tool": "translationNotes",
      "groupId": "figs-personification",
      "glQuote": "General Information:",
      "occurrence": 0
    }
  },
  {
    "comments": false,
    "reminders": false,
    "selections": false,
    "verseEdits": false,
    "contextId": {
      "occurrenceNote": "This is wisdom speaking about herself. (See: [[rc://en/ta/man/translate/figs-personification]])",
      "reference": {
        "bookId": "pro",
        "chapter": 8,
        "verse": 26
      },
      "tool": "translationNotes",
      "groupId": "figs-personification",
      "glQuote": "I was born",
      "occurrence": 0
    }
  },
  {
    "comments": false,
    "reminders": false,
    "selections": false,
    "verseEdits": false,
    "contextId": {
      "occurrenceNote": "This is wisdom speaking about herself. (See: [[rc://en/ta/man/translate/figs-personification]])",
      "reference": {
        "bookId": "pro",
        "chapter": 8,
        "verse": 27
      },
      "tool": "translationNotes",
      "groupId": "figs-personification",
      "glQuote": "I was there",
      "occurrence": 0
    }
  },
  {
    "comments": false,
    "reminders": false,
    "selections": false,
    "verseEdits": false,
    "contextId": {
      "occurrenceNote": "Wisdom continues to speak. (See: [[rc://en/ta/man/translate/figs-personification]])",
      "reference": {
        "bookId": "pro",
        "chapter": 8,
        "verse": 28
      },
      "tool": "translationNotes",
      "groupId": "figs-personification",
      "glQuote": "General Information:",
      "occurrence": 0
    }
  },
  {
    "comments": false,
    "reminders": false,
    "selections": false,
    "verseEdits": false,
    "contextId": {
      "occurrenceNote": "This is still wisdom speaking. Wisdom now says she was right next to Yahweh, implying that she was his assistant in creating the world. (See: [[rc://en/ta/man/translate/figs-personification]])",
      "reference": {
        "bookId": "pro",
        "chapter": 8,
        "verse": 30
      },
      "tool": "translationNotes",
      "groupId": "figs-personification",
      "glQuote": "I was beside him",
      "occurrence": 0
    }
  },
  {
    "comments": false,
    "reminders": false,
    "selections": false,
    "verseEdits": false,
    "contextId": {
      "occurrenceNote": "This is still wisdom talking about herself. (See: [[rc://en/ta/man/translate/figs-personification]])",
      "reference": {
        "bookId": "pro",
        "chapter": 8,
        "verse": 32
      },
      "tool": "translationNotes",
      "groupId": "figs-personification",
      "glQuote": "listen to me",
      "occurrence": 0
    }
  },
  {
    "comments": false,
    "reminders": false,
    "selections": false,
    "verseEdits": false,
    "contextId": {
      "occurrenceNote": "This is still wisdom talking about herself. (See: [[rc://en/ta/man/translate/figs-personification]])",
      "reference": {
        "bookId": "pro",
        "chapter": 8,
        "verse": 35
      },
      "tool": "translationNotes",
      "groupId": "figs-personification",
      "glQuote": "finds me",
      "occurrence": 0
    }
  },
  {
    "comments": false,
    "reminders": false,
    "selections": false,
    "verseEdits": false,
    "contextId": {
      "occurrenceNote": "This is still wisdom talking about herself. (See: [[rc://en/ta/man/translate/figs-personification]])",
      "reference": {
        "bookId": "pro",
        "chapter": 8,
        "verse": 36
      },
      "tool": "translationNotes",
      "groupId": "figs-personification",
      "glQuote": "hate me",
      "occurrence": 0
    }
  },
  {
    "comments": false,
    "reminders": false,
    "selections": false,
    "verseEdits": false,
    "contextId": {
      "occurrenceNote": "These verses begin a parable in which wisdom is imagined to be a woman who is giving good advice to people. (See: [[rc://en/ta/man/translate/figs-personification]])",
      "reference": {
        "bookId": "pro",
        "chapter": 9,
        "verse": 1
      },
      "tool": "translationNotes",
      "groupId": "figs-personification",
      "glQuote": "General Information:",
      "occurrence": 0
    }
  },
  {
    "comments": false,
    "reminders": false,
    "selections": false,
    "verseEdits": false,
    "contextId": {
      "occurrenceNote": "The writer speaks about wisdom as if it were a woman who has built her own house. (See: [[rc://en/ta/man/translate/figs-personification]])",
      "reference": {
        "bookId": "pro",
        "chapter": 9,
        "verse": 1
      },
      "tool": "translationNotes",
      "groupId": "figs-personification",
      "glQuote": "Wisdom has built",
      "occurrence": 0
    }
  },
  {
    "comments": false,
    "reminders": false,
    "selections": false,
    "verseEdits": false,
    "contextId": {
      "occurrenceNote": "These verses begin to give the message of Wisdom, who is personified as a woman. (See: [[rc://en/ta/man/translate/figs-personification]])",
      "reference": {
        "bookId": "pro",
        "chapter": 9,
        "verse": 3
      },
      "tool": "translationNotes",
      "groupId": "figs-personification",
      "glQuote": "General Information:",
      "occurrence": 0
    }
  },
  {
    "comments": false,
    "reminders": false,
    "selections": false,
    "verseEdits": false,
    "contextId": {
      "occurrenceNote": "Wisdom, personified as a woman, continues to speak here. (See: [[rc://en/ta/man/translate/figs-personification]])",
      "reference": {
        "bookId": "pro",
        "chapter": 9,
        "verse": 11
      },
      "tool": "translationNotes",
      "groupId": "figs-personification",
      "glQuote": "through me",
      "occurrence": 0
    }
  },
  {
    "comments": false,
    "reminders": false,
    "selections": false,
    "verseEdits": false,
    "contextId": {
      "occurrenceNote": "These verses begin to describe foolishness, which is also personified as a woman. (See: [[rc://en/ta/man/translate/figs-personification]])",
      "reference": {
        "bookId": "pro",
        "chapter": 9,
        "verse": 13
      },
      "tool": "translationNotes",
      "groupId": "figs-personification",
      "glQuote": "General Information:",
      "occurrence": 0
    }
  },
  {
    "comments": false,
    "reminders": false,
    "selections": false,
    "verseEdits": false,
    "contextId": {
      "occurrenceNote": "It is possible to translate \"foolishness\" as a description such as \"A foolish woman.\" However, if a language allows wisdom to be personified, as in the previous part of this chapter, it may also allow foolishness to be personified. Alternate translation: \"The woman Foolishness\" (See: [[rc://en/ta/man/translate/figs-personification]])",
      "reference": {
        "bookId": "pro",
        "chapter": 9,
        "verse": 13
      },
      "tool": "translationNotes",
      "groupId": "figs-personification",
      "glQuote": "The woman of foolishness",
      "occurrence": 0
    }
  },
  {
    "comments": false,
    "reminders": false,
    "selections": false,
    "verseEdits": false,
    "contextId": {
      "occurrenceNote": "Love acts like a person who quiets trouble between people instead of stirring it up. (See: [[rc://en/ta/man/translate/figs-personification]])",
      "reference": {
        "bookId": "pro",
        "chapter": 10,
        "verse": 12
      },
      "tool": "translationNotes",
      "groupId": "figs-personification",
      "glQuote": "love covers over",
      "occurrence": 0
    }
  },
  {
    "comments": false,
    "reminders": false,
    "selections": false,
    "verseEdits": false,
    "contextId": {
      "occurrenceNote": "\"Righteousness\" represents a way of life approved by Yahweh. This quality acts like a person who protects. Alternate translation: \"A way of life approved by Yahweh protects\" (See: [[rc://en/ta/man/translate/figs-personification]])",
      "reference": {
        "bookId": "pro",
        "chapter": 13,
        "verse": 6
      },
      "tool": "translationNotes",
      "groupId": "figs-personification",
      "glQuote": "Righteousness protects those",
      "occurrence": 0
    }
  },
  {
    "comments": false,
    "reminders": false,
    "selections": false,
    "verseEdits": false,
    "contextId": {
      "occurrenceNote": "Here \"wickedness\" represents an evil conduct of life. This quality acts like a person who turns away those who commit sin. Alternate translation: \"wickedness turns sinners away from a successful path\" or \"wickedness ruins sinners' lives\" (See: [[rc://en/ta/man/translate/figs-personification]])",
      "reference": {
        "bookId": "pro",
        "chapter": 13,
        "verse": 6
      },
      "tool": "translationNotes",
      "groupId": "figs-personification",
      "glQuote": "wickedness turns away those who commit sin",
      "occurrence": 0
    }
  },
  {
    "comments": false,
    "reminders": false,
    "selections": false,
    "verseEdits": false,
    "contextId": {
      "occurrenceNote": "\"Disaster\" is given human characteristics like the ability to run. Alternate translation: \"Sinners have trouble wherever they go\" (See: [[rc://en/ta/man/translate/figs-personification]])",
      "reference": {
        "bookId": "pro",
        "chapter": 13,
        "verse": 21
      },
      "tool": "translationNotes",
      "groupId": "figs-personification",
      "glQuote": "Disaster runs after sinners",
      "occurrence": 0
    }
  },
  {
    "comments": false,
    "reminders": false,
    "selections": false,
    "verseEdits": false,
    "contextId": {
      "occurrenceNote": "The word \"she\" refers to wisdom. (See: [[rc://en/ta/man/translate/figs-personification]])",
      "reference": {
        "bookId": "pro",
        "chapter": 14,
        "verse": 33
      },
      "tool": "translationNotes",
      "groupId": "figs-personification",
      "glQuote": "she",
      "occurrence": 0
    }
  },
  {
    "comments": false,
    "reminders": false,
    "selections": false,
    "verseEdits": false,
    "contextId": {
      "occurrenceNote": "The writer speaks of the appetite as if it were a person who works on behalf of the laborer. This means that the person who labors is motivated by his desire to eat. Alternate translation: \"The laborer works to satisfy his appetite\" (See: [[rc://en/ta/man/translate/figs-personification]])",
      "reference": {
        "bookId": "pro",
        "chapter": 16,
        "verse": 26
      },
      "tool": "translationNotes",
      "groupId": "figs-personification",
      "glQuote": "The laborer's appetite works for him",
      "occurrence": 0
    }
  },
  {
    "comments": false,
    "reminders": false,
    "selections": false,
    "verseEdits": false,
    "contextId": {
      "occurrenceNote": "The writer speaks of \"hunger\" as if it were a person who urges the laborer to continue working. Alternate translation: \"he keeps on working because he is hungry\" (See: [[rc://en/ta/man/translate/figs-personification]])",
      "reference": {
        "bookId": "pro",
        "chapter": 16,
        "verse": 26
      },
      "tool": "translationNotes",
      "groupId": "figs-personification",
      "glQuote": "his hunger urges him on",
      "occurrence": 0
    }
  },
  {
    "comments": false,
    "reminders": false,
    "selections": false,
    "verseEdits": false,
    "contextId": {
      "occurrenceNote": "Here \"evil\" is spoken of as if it were a person who would not leave the man's house. Here the word \"house\" may be taken literally, but it is also a metonym for his family. Alternate translation: \"bad things will continue to happen to him and his family\" or \"bad things will never stop happening to him and his family\" (See: [[rc://en/ta/man/translate/figs-personification]] and [[rc://en/ta/man/translate/figs-metonymy]])",
      "reference": {
        "bookId": "pro",
        "chapter": 17,
        "verse": 13
      },
      "tool": "translationNotes",
      "groupId": "figs-personification",
      "glQuote": "evil will never leave his house",
      "occurrence": 0
    }
  },
  {
    "comments": false,
    "reminders": false,
    "selections": false,
    "verseEdits": false,
    "contextId": {
      "occurrenceNote": "This speaks of a person disagreeing with sound judgment as if \"sound judgment\" were a person he fought with. Alternate translation: \"he disagrees with all sound judgment\" (See: [[rc://en/ta/man/translate/figs-personification]])",
      "reference": {
        "bookId": "pro",
        "chapter": 18,
        "verse": 1
      },
      "tool": "translationNotes",
      "groupId": "figs-personification",
      "glQuote": "quarrels with all sound judgment",
      "occurrence": 0
    }
  },
  {
    "comments": false,
    "reminders": false,
    "selections": false,
    "verseEdits": false,
    "contextId": {
      "occurrenceNote": "Here \"contempt,\" \"shame,\" and \"reproach\" are spoken of as if they are people who accompany a wicked man. Possible meanings are 1) people show contempt towards the wicked man and cause him to feel shame and reproach. Alternate translation: \"people feel contempt for him along with shame and reproach\" or 2) the wicked man shows contempt for others and causes them to feel shame and reproach. Alternate translation: \"he shows his contempt for other people and causes them to feel shame and reproach\" (See: [[rc://en/ta/man/translate/figs-personification]])",
      "reference": {
        "bookId": "pro",
        "chapter": 18,
        "verse": 3
      },
      "tool": "translationNotes",
      "groupId": "figs-personification",
      "glQuote": "contempt comes with him—along with shame and reproach",
      "occurrence": 0
    }
  },
  {
    "comments": false,
    "reminders": false,
    "selections": false,
    "verseEdits": false,
    "contextId": {
      "occurrenceNote": "This speaks of how laziness causes a person to sleep a lot as if laziness forcefully throws the person into sleep. Alternate translation: \"Laziness makes a person sleep a lot\" or \"A lazy person sleeps a lot\" (See: [[rc://en/ta/man/translate/figs-personification]])",
      "reference": {
        "bookId": "pro",
        "chapter": 19,
        "verse": 15
      },
      "tool": "translationNotes",
      "groupId": "figs-personification",
      "glQuote": "Laziness throws a person into a deep sleep",
      "occurrence": 0
    }
  },
  {
    "comments": false,
    "reminders": false,
    "selections": false,
    "verseEdits": false,
    "contextId": {
      "occurrenceNote": "The writer speaks as though violence were a person who could drag other people away. God will punish wicked people who harm their innocent neighbors. (See: [[rc://en/ta/man/translate/figs-personification]])",
      "reference": {
        "bookId": "pro",
        "chapter": 21,
        "verse": 7
      },
      "tool": "translationNotes",
      "groupId": "figs-personification",
      "glQuote": "The violence of the wicked will drag them away",
      "occurrence": 0
    }
  },
  {
    "comments": false,
    "reminders": false,
    "selections": false,
    "verseEdits": false,
    "contextId": {
      "occurrenceNote": "The writer speaks of a person's appetite, the physical desire for food and drink, as if it were a person who could desire something. The word \"wicked\" is a nominal adjective that refers to evil people, and the word \"evil\" is a nominal adjective that refers to evil deeds. Alternate translation: \"Evil people desire to do evil deeds just as they desire to eat and drink\" (See: [[rc://en/ta/man/translate/figs-personification]] and [[rc://en/ta/man/translate/figs-nominaladj]])",
      "reference": {
        "bookId": "pro",
        "chapter": 21,
        "verse": 10
      },
      "tool": "translationNotes",
      "groupId": "figs-personification",
      "glQuote": "The appetite of the wicked craves evil",
      "occurrence": 0
    }
  },
  {
    "comments": false,
    "reminders": false,
    "selections": false,
    "verseEdits": false,
    "contextId": {
      "occurrenceNote": "The writer speaks of what a person wants as if it were a person who could kill a lazy person. Here the lazy person wants to be idle and not work. Alternate translation: \"A lazy person only wants to be idle, and because of that he will die\" or \"A lazy person will die because he does not want to work\" (See: [[rc://en/ta/man/translate/figs-personification]] and [[rc://en/ta/man/translate/figs-nominaladj]])",
      "reference": {
        "bookId": "pro",
        "chapter": 21,
        "verse": 25
      },
      "tool": "translationNotes",
      "groupId": "figs-personification",
      "glQuote": "The desire of the lazy kills him",
      "occurrence": 0
    }
  },
  {
    "comments": false,
    "reminders": false,
    "selections": false,
    "verseEdits": false,
    "contextId": {
      "occurrenceNote": "The word \"slumber\" is an exaggeration for a person spending so much time enjoying food and drink that he does not do necessary work. This activity is spoken of as if it were a parent putting clothes on a child. Alternate translation: \"because they spend so much time eating and drinking, they will do no work and so will become poor\" (See: [[rc://en/ta/man/translate/figs-personification]] and [[rc://en/ta/man/translate/figs-hyperbole]])",
      "reference": {
        "bookId": "pro",
        "chapter": 23,
        "verse": 21
      },
      "tool": "translationNotes",
      "groupId": "figs-personification",
      "glQuote": "slumber will clothe them with rags",
      "occurrence": 0
    }
  },
  {
    "comments": false,
    "reminders": false,
    "selections": false,
    "verseEdits": false,
    "contextId": {
      "occurrenceNote": "The writer speaks as if \"calamity\" were a person who could do bad things to other people. These words can be translated in active form. Alternate translation: \"God will use calamity to bring down the wicked people\" (See: [[rc://en/ta/man/translate/figs-personification]] and [[rc://en/ta/man/translate/figs-activepassive]])",
      "reference": {
        "bookId": "pro",
        "chapter": 24,
        "verse": 16
      },
      "tool": "translationNotes",
      "groupId": "figs-personification",
      "glQuote": "wicked people are brought down by calamity",
      "occurrence": 0
    }
  },
  {
    "comments": false,
    "reminders": false,
    "selections": false,
    "verseEdits": false,
    "contextId": {
      "occurrenceNote": "Gifts are spoken of as if they were people who could move by themselves. The abstract noun \"goodness\" can be translated as an adjective. Alternate translation: \"people will give them good gifts\" (See: [[rc://en/ta/man/translate/figs-personification andfigs-abstractnouns]] and ",
      "reference": {
        "bookId": "pro",
        "chapter": 24,
        "verse": 25
      },
      "tool": "translationNotes",
      "groupId": "figs-personification",
      "glQuote": "gifts of goodness will come to them",
      "occurrence": 0
    }
  },
  {
    "comments": false,
    "reminders": false,
    "selections": false,
    "verseEdits": false,
    "contextId": {
      "occurrenceNote": "Some translations read, \"poverty comes upon you like a robber.\" Poverty is spoken of as if it were a person or animal that can attack a lazy person. (See: [[rc://en/ta/man/translate/figs-personification]])",
      "reference": {
        "bookId": "pro",
        "chapter": 24,
        "verse": 34
      },
      "tool": "translationNotes",
      "groupId": "figs-personification",
      "glQuote": "poverty comes marching upon you",
      "occurrence": 0
    }
  },
  {
    "comments": false,
    "reminders": false,
    "selections": false,
    "verseEdits": false,
    "contextId": {
      "occurrenceNote": "The writer speaks as if a rod and reproof were people who could give wisdom as a physical gift. Alternate translation: \"If a parent uses the rod on his child and reproves him, the child will become wise\" or \"If parents discipline their child and tell him when he has done wrong, the child will learn to live wisely\" (See: [[rc://en/ta/man/translate/figs-personification]])",
      "reference": {
        "bookId": "pro",
        "chapter": 29,
        "verse": 15
      },
      "tool": "translationNotes",
      "groupId": "figs-personification",
      "glQuote": "The rod and reproof give wisdom",
      "occurrence": 0
    }
  },
  {
    "comments": false,
    "reminders": false,
    "selections": false,
    "verseEdits": false,
    "contextId": {
      "occurrenceNote": "Land that is no longer producing food because there has been no rain is spoken of as if it were a person who does not have enough water to drink. (See: [[rc://en/ta/man/translate/figs-personification]])",
      "reference": {
        "bookId": "pro",
        "chapter": 30,
        "verse": 16
      },
      "tool": "translationNotes",
      "groupId": "figs-personification",
      "glQuote": "land that is never satisfied with water",
      "occurrence": 0
    }
  }
]
